{
  "Test Competitor": [
    {
      "name": "Amazon Sign-In",
      "normalized_name": "amazon_sign_in",
      "price": "N/A",
      "url": "https://www.amazon.com/iss/credit/rewardscardmember?plattr=CBFOOT&ref_=footer_cbcc",
      "category": "unknown"
    },
    {
      "name": "Recalls and Product Safety Alerts",
      "normalized_name": "recalls_and_product_safety_alerts",
      "price": "$10",
      "url": "https://www.amazon.com/product-safety-alerts?ref_=footer_bsx_ypsa",
      "category": "unknown"
    },
    {
      "name": "Amazon Registry & Gifting",
      "normalized_name": "amazon_registry___gifting",
      "price": "$10",
      "url": "https://www.amazon.com/registries?ref_=nav_footer_registry_giftlist_desktop",
      "category": "unknown"
    },
    {
      "name": "Unknown Product",
      "normalized_name": "unknown_product",
      "price": "$10",
      "url": "https://www.amazon.com/gift-cards/b/?ie=UTF8&node=2238192011&ref_=nav_cs_gc",
      "category": "unknown"
    },
    {
      "name": "Amazon.com",
      "normalized_name": "amazon_com",
      "price": "N/A",
      "url": "https://www.amazon.com/dp/product/B084KP3NG6?plattr=SCFOOT&ref_=footer_ACB",
      "category": "unknown"
    },
    {
      "name": "Amazon Sign-In",
      "normalized_name": "amazon_sign_in",
      "price": "N/A",
      "url": "https://www.amazon.com/credit/storecard/member?plattr=PLCCFOOT&ref_=footer_plcc",
      "category": "unknown"
    },
    {
      "name": "Unknown Product",
      "normalized_name": "unknown_product",
      "price": "$10",
      "url": "https://www.amazon.com/gift-cards#skippedLink",
      "category": "unknown"
    },
    {
      "name": "Unknown Product",
      "normalized_name": "unknown_product",
      "price": "$10",
      "url": "https://www.amazon.com/gift-cards",
      "category": "unknown"
    }
  ],
  "Test Competitor2": [
    {
      "name": "Anniversary Gift Cards \u2013 The Best Gift for Anniversary",
      "normalized_name": "anniversary_gift_cards___the_best_gift_for_anniversary",
      "price": "\u20b91",
      "url": "https://www.woohoo.in/by-occasion/gift-cards-for-anniversary",
      "category": "unknown"
    },
    {
      "name": "Rakshabandhan Gift Cards & Gift Vouchers | Woohoo.in",
      "normalized_name": "rakshabandhan_gift_cards___gift_vouchers___woohoo_in",
      "price": "\u20b950.00",
      "url": "https://www.woohoo.in/by-occasion/gift-cards-for-rakshabandhan",
      "category": "unknown"
    },
    {
      "name": "Birthday Gift Cards | Get 100 Woohoo Coins | Promo Code - GET100",
      "normalized_name": "birthday_gift_cards___get_100_woohoo_coins___promo_code___get100",
      "price": "\u20b9100.00",
      "url": "https://www.woohoo.in/by-occasion/gift-cards-for-birthday",
      "category": "unknown"
    },
    {
      "name": "Woohoo (@woohoogifting) \u2022 Instagram photos and videos",
      "normalized_name": "woohoo___woohoogifting____instagram_photos_and_videos",
      "price": "N/A",
      "url": "https://instagram.com/woohoogifting",
      "category": "unknown"
    },
    {
      "name": "Wedding Gift Cards | Get 100 Woohoo Coins | Promo Code - GET100",
      "normalized_name": "wedding_gift_cards___get_100_woohoo_coins___promo_code___get100",
      "price": "\u20b9960.00",
      "url": "https://www.woohoo.in/by-occasion/gift-cards-for-wedding",
      "category": "unknown"
    },
    {
      "name": "Movies & Entertainment Gift Cards | Woohoo.in",
      "normalized_name": "movies___entertainment_gift_cards___woohoo_in",
      "price": "\u20b9550.00",
      "url": "https://www.woohoo.in/by-category/entertainment-gift-cards",
      "category": "unknown"
    },
    {
      "name": "Gift Cards & Gift Vouchers - 300+ Brands - 1000+ Offers | Woohoo.in",
      "normalized_name": "gift_cards___gift_vouchers___300__brands___1000__offers___woohoo_in",
      "price": "\u20b9200.00",
      "url": "https://www.woohoo.in/gift-cards",
      "category": "unknown"
    },
    {
      "name": "Experience E-Gift Cards  | Gift an Experience - Woohoo.in",
      "normalized_name": "experience_e_gift_cards____gift_an_experience___woohoo_in",
      "price": "\u20b97",
      "url": "https://www.woohoo.in/experience-e-gift-cards",
      "category": "unknown"
    },
    {
      "name": "Return Gifts | The Perfect Return Gift for Every Celebration",
      "normalized_name": "return_gifts___the_perfect_return_gift_for_every_celebration",
      "price": "N/A",
      "url": "https://www.woohoo.in/return-gifts",
      "category": "unknown"
    },
    {
      "name": "Corporate Gift Cards & Gift Vouchers - 150 + Brands | Woohoo.in",
      "normalized_name": "corporate_gift_cards___gift_vouchers___150___brands___woohoo_in",
      "price": "N/A",
      "url": "https://www.woohoo.in/employee-partner-gifts",
      "category": "unknown"
    },
    {
      "name": "Telegram: View @Woohoogifting",
      "normalized_name": "telegram__view__woohoogifting",
      "price": "N/A",
      "url": "https://t.me/Woohoogifting",
      "category": "unknown"
    },
    {
      "name": "",
      "normalized_name": "",
      "price": "\u20b9700.00",
      "url": "https://www.woohoo.in/by-category/gaming-gift-cards",
      "category": "unknown"
    },
    {
      "name": "Restaurant Gift Cards - Gift a Dining Experience with Gift Cards",
      "normalized_name": "restaurant_gift_cards___gift_a_dining_experience_with_gift_cards",
      "price": "\u20b9240.00",
      "url": "https://www.woohoo.in/by-category/restaurants-gift-cards",
      "category": "unknown"
    },
    {
      "name": "Load Gift Card",
      "normalized_name": "load_gift_card",
      "price": "\u20b9500.00",
      "url": "https://www.woohoo.in/loadcard",
      "category": "unknown"
    },
    {
      "name": "Unknown Product",
      "normalized_name": "unknown_product",
      "price": "N/A",
      "url": "https://twitter.com/woohoogifting",
      "category": "unknown"
    },
    {
      "name": "Christmas Gift Cards - 200+ Brands & 600+ Offers | Woohoo.in",
      "normalized_name": "christmas_gift_cards___200__brands___600__offers___woohoo_in",
      "price": "\u20b9300.00",
      "url": "https://www.woohoo.in/christmas-gift-cards",
      "category": "unknown"
    },
    {
      "name": "Travel Gift Cards & E-Gift Vouchers",
      "normalized_name": "travel_gift_cards___e_gift_vouchers",
      "price": "\u20b92",
      "url": "https://www.woohoo.in/by-category/travel-gift-cards",
      "category": "unknown"
    },
    {
      "name": "WoohooGifting",
      "normalized_name": "woohoogifting",
      "price": "N/A",
      "url": "https://facebook.com/woohoogifting",
      "category": "unknown"
    },
    {
      "name": "Corporate Gifts | Customised Corporate Gifting Solutions",
      "normalized_name": "corporate_gifts___customised_corporate_gifting_solutions",
      "price": "N/A",
      "url": "https://www.woohoo.in/corporate-gifting",
      "category": "unknown"
    },
    {
      "name": "E-Gift Cards - Send a Digital E-Gift Card Instantly | Woohoo.in",
      "normalized_name": "e_gift_cards___send_a_digital_e_gift_card_instantly___woohoo_in",
      "price": "\u20b9300.00",
      "url": "https://www.woohoo.in/e-gift-cards",
      "category": "unknown"
    }
  ],
  "Test Competitor3": [
    {
      "name": "Digital Gift Cards - Buy Digital Gift Cards Online at Best Prices In India | Flipkart.com",
      "normalized_name": "digital_gift_cards___buy_digital_gift_cards_online_at_best_prices_in_india___flipkart_com",
      "price": "\u20b95",
      "url": "https://www.flipkart.com/vas/gift-cards/digital-gift-cards/pr?sid=mcd%2C1ob%2Cdci&p%5B%5D=facets.price_range.from%3D2500&p%5B%5D=facets.price_range.to%3D5000&p%5B%5D=facets.type%255B%255D%3DTravel&p%5B%5D=facets.type%255B%255D%3DEntertainment&p%5B%5D=facets.type%255B%255D%3DSpa%2B%2526%2BSalon&p%5B%5D=facets.type%255B%255D%3DElectronics&p%5B%5D=facets.type%255B%255D%3DHome%2B%2526%2BKitchen&p%5B%5D=facets.type%255B%255D%3DFood%2B%2526%2BBeverages&p%5B%5D=facets.type%255B%255D%3DApps%2B%2526%2BSoftware&p%5B%5D=facets.type%255B%255D%3DGold%2Band%2BDiamonds&p%5B%5D=facets.type%255B%255D%3DLifestyle&pageUID=175275223448383&otracker=clp_creative_card_3_7.creativeCard.CREATIVE_CARD_the-gift-card-store_CZADV4FTBLXG&fm=neo%2Fmerchandising&iid=M_6386fec3-c4cd-4b4a-b1ca-1d38a6b1651a_7.CZADV4FTBLXG&ppt=None&ppn=None&ssid=we9qihzogg0000001771434649458",
      "category": "unknown"
    },
    {
      "name": "Flipkart Digital Gift Card Price in India - Buy Flipkart Digital Gift Card online at Flipkart.com",
      "normalized_name": "flipkart_digital_gift_card_price_in_india___buy_flipkart_digital_gift_card_online_at_flipkart_com",
      "price": "\u20b910",
      "url": "https://www.flipkart.com/flipkart-digital-gift-card/p/itm756915bf8bfe1?pid=GVOG9ANVSZC5AZN7&lid=LSTGVOG9ANVSZC5AZN74NKHLB&marketplace=FLIPKART&sattr[]=occasion&sattr[]=denomination&st=occasion&param=4864&otracker=clp_creative_card_1_2.creativeCard.CREATIVE_CARD_the-gift-card-store_UUIFMOA6VPYT&fm=neo%2Fmerchandising&iid=M_6386fec3-c4cd-4b4a-b1ca-1d38a6b1651a_2.UUIFMOA6VPYT&ppt=None&ppn=None&ssid=we9qihzogg0000001771434649458&ov_redirect=true",
      "category": "unknown"
    },
    {
      "name": "Flipkart Digital Gift Card Price in India - Buy Flipkart Digital Gift Card online at Flipkart.com",
      "normalized_name": "flipkart_digital_gift_card_price_in_india___buy_flipkart_digital_gift_card_online_at_flipkart_com",
      "price": "\u20b99",
      "url": "https://www.flipkart.com/flipkart-digital-gift-card/p/itm0292ec029dcd7?pid=GVOHFVU4GQEWEZ5V&lid=LSTGVOHFVU4GQEWEZ5VHAJ7QD&otracker=clp_banner_3_5.bannerX3.BANNER_the-gift-card-store_BD1XOKCDAF03&fm=neo%2Fmerchandising&iid=M_6386fec3-c4cd-4b4a-b1ca-1d38a6b1651a_5.BD1XOKCDAF03&ppt=None&ppn=None&ssid=we9qihzogg0000001771434649458&ov_redirect=true",
      "category": "unknown"
    },
    {
      "name": "Flipkart Digital Gift Card Price in India - Buy Flipkart Digital Gift Card online at Flipkart.com",
      "normalized_name": "flipkart_digital_gift_card_price_in_india___buy_flipkart_digital_gift_card_online_at_flipkart_com",
      "price": "\u20b910",
      "url": "https://www.flipkart.com/flipkart-digital-gift-card/p/itm70687d7fabdab?pid=GVOGY7ZCEZSVZYYW&lid=LSTGVOGY7ZCEZSVZYYW3GT3L9&otracker=clp_banner_2_4.bannerX3.BANNER_the-gift-card-store_NJJOGX5Z369V&fm=neo%2Fmerchandising&iid=M_6386fec3-c4cd-4b4a-b1ca-1d38a6b1651a_4.NJJOGX5Z369V&ppt=None&ppn=None&ssid=we9qihzogg0000001771434649458&ov_redirect=true",
      "category": "unknown"
    },
    {
      "name": "Buy Products Online at Best Price in India - All Categories | Flipkart.com",
      "normalized_name": "buy_products_online_at_best_price_in_india___all_categories___flipkart_com",
      "price": "N/A",
      "url": "https://www.flipkart.com/giftcard-b2b-at-store?param=65456863&pageUID=175275029807293&otracker=clp_creative_card_3_2.creativeCard.CREATIVE_CARD_the-gift-card-store_HS7L6CAJD2AQ&fm=neo%2Fmerchandising&iid=M_6386fec3-c4cd-4b4a-b1ca-1d38a6b1651a_2.HS7L6CAJD2AQ&ppt=None&ppn=None&ssid=we9qihzogg0000001771434649458",
      "category": "unknown"
    },
    {
      "name": "Flipkart Digital Gift Card Price in India - Buy Flipkart Digital Gift Card online at Flipkart.com",
      "normalized_name": "flipkart_digital_gift_card_price_in_india___buy_flipkart_digital_gift_card_online_at_flipkart_com",
      "price": "\u20b91",
      "url": "https://www.flipkart.com/flipkart-digital-gift-card/p/itme2edb41bd57ca?pid=GVOHC4FKUVZMQKGB&lid=LSTGVOHC4FKUVZMQKGBZBIDKM&otracker=clp_banner_3_4.bannerX3.BANNER_the-gift-card-store_RLKG5D3PQURI&fm=neo%2Fmerchandising&iid=M_6386fec3-c4cd-4b4a-b1ca-1d38a6b1651a_4.RLKG5D3PQURI&ppt=None&ppn=None&ssid=we9qihzogg0000001771434649458&ov_redirect=true",
      "category": "unknown"
    },
    {
      "name": "Flipkart Digital Gift Card Price in India - Buy Flipkart Digital Gift Card online at Flipkart.com",
      "normalized_name": "flipkart_digital_gift_card_price_in_india___buy_flipkart_digital_gift_card_online_at_flipkart_com",
      "price": "\u20b910",
      "url": "https://www.flipkart.com/flipkart-digital-gift-card/p/itm3779ca1a3e5dc?pid=GVOGY7Y7PBYH4NDF&lid=LSTGVOGY7Y7PBYH4NDFXENO2Z&otracker=clp_banner_1_5.bannerX3.BANNER_the-gift-card-store_VRZTW9L5LEP1&fm=neo%2Fmerchandising&iid=M_6386fec3-c4cd-4b4a-b1ca-1d38a6b1651a_5.VRZTW9L5LEP1&ppt=None&ppn=None&ssid=we9qihzogg0000001771434649458&ov_redirect=true",
      "category": "unknown"
    },
    {
      "name": "Flipkart Physical Gift Card Price in India - Buy Flipkart Physical Gift Card online at Flipkart.com",
      "normalized_name": "flipkart_physical_gift_card_price_in_india___buy_flipkart_physical_gift_card_online_at_flipkart_com",
      "price": "\u20b92",
      "url": "https://www.flipkart.com/flipkart-digital-gift-card/p/itm756915bf8bfe1?pid=PGVFQPKPH8YGWHGE&lid=LSTPGVFQPKPH8YGWHGERDUU3C&marketplace=FLIPKART&sattr%5B%5D=occasion&sattr%5B%5D=denomination&st=denomination&param=8243456&pageUID=1763356008306846&otracker=clp_creative_card_2_2.creativeCard.CREATIVE_CARD_the-gift-card-store_CDBFASJP40LS&fm=neo%2Fmerchandising&iid=M_6386fec3-c4cd-4b4a-b1ca-1d38a6b1651a_2.CDBFASJP40LS&ppt=None&ppn=None&ssid=we9qihzogg0000001771434649458&ov_redirect=true",
      "category": "unknown"
    },
    {
      "name": "Digital Gift Cards - Buy Digital Gift Cards Online at Best Prices In India | Flipkart.com",
      "normalized_name": "digital_gift_cards___buy_digital_gift_cards_online_at_best_prices_in_india___flipkart_com",
      "price": "\u20b98",
      "url": "https://www.flipkart.com/vas/gift-cards/digital-gift-cards/pr?sid=mcd%2C1ob%2Cdci&p%5B%5D=facets.price_range.from%3D5000&p%5B%5D=facets.price_range.to%3D10000&sort=recency_desc&pageUID=1752752301536836&otracker=clp_creative_card_2_7.creativeCard.CREATIVE_CARD_the-gift-card-store_D6L4S1RCCTE9&fm=neo%2Fmerchandising&iid=M_6386fec3-c4cd-4b4a-b1ca-1d38a6b1651a_7.D6L4S1RCCTE9&ppt=None&ppn=None&ssid=we9qihzogg0000001771434649458",
      "category": "unknown"
    },
    {
      "name": "Flipkart Digital Gift Card Price in India - Buy Flipkart Digital Gift Card online at Flipkart.com",
      "normalized_name": "flipkart_digital_gift_card_price_in_india___buy_flipkart_digital_gift_card_online_at_flipkart_com",
      "price": "\u20b925",
      "url": "https://www.flipkart.com/flipkart-digital-gift-card/p/itm0fe15be653863?pid=GVOGCEMDSXTFWXQR&lid=LSTGVOGCEMDSXTFWXQRRWEJYU&otracker=clp_banner_1_1.banner.BANNER_the-gift-card-store_6A0TMSVPNSUV",
      "category": "unknown"
    },
    {
      "name": "Flipkart reCAPTCHA",
      "normalized_name": "flipkart_recaptcha",
      "price": "N/A",
      "url": "https://m.flipkart.com/rv/wallet/egv/add?otracker=clp_creative_card_4_2.creativeCard.CREATIVE_CARD_the-gift-card-store_RYQN8EMRPQXZ&fm=neo%2Fmerchandising&iid=M_6386fec3-c4cd-4b4a-b1ca-1d38a6b1651a_2.RYQN8EMRPQXZ&ppt=None&ppn=None&ssid=we9qihzogg0000001771434649458",
      "category": "unknown"
    },
    {
      "name": "Flipkart Digital Gift Card Price in India - Buy Flipkart Digital Gift Card online at Flipkart.com",
      "normalized_name": "flipkart_digital_gift_card_price_in_india___buy_flipkart_digital_gift_card_online_at_flipkart_com",
      "price": "\u20b910",
      "url": "https://www.flipkart.com/flipkart-digital-gift-card/p/itm24438006fcde4?pid=GVOGY7YPQK2DHM4T&lid=LSTGVOGY7YPQK2DHM4TOLIGHY&otracker=clp_banner_1_4.bannerX3.BANNER_the-gift-card-store_FBM0MBCR0XD8&fm=neo%2Fmerchandising&iid=M_6386fec3-c4cd-4b4a-b1ca-1d38a6b1651a_4.FBM0MBCR0XD8&ppt=None&ppn=None&ssid=we9qihzogg0000001771434649458&ov_redirect=true",
      "category": "unknown"
    },
    {
      "name": "Flipkart Digital Gift Card Price in India - Buy Flipkart Digital Gift Card online at Flipkart.com",
      "normalized_name": "flipkart_digital_gift_card_price_in_india___buy_flipkart_digital_gift_card_online_at_flipkart_com",
      "price": "\u20b925",
      "url": "https://www.flipkart.com/flipkart-digital-gift-card/p/itm1848fb91eb735?pid=GVOGC99R8JQ5UKFG&lid=LSTGVOGC99R8JQ5UKFG6PGSPI&otracker=clp_banner_2_5.bannerX3.BANNER_the-gift-card-store_H06HUH6EVPS0&fm=neo%2Fmerchandising&iid=M_6386fec3-c4cd-4b4a-b1ca-1d38a6b1651a_5.H06HUH6EVPS0&ppt=None&ppn=None&ssid=we9qihzogg0000001771434649458&ov_redirect=true",
      "category": "unknown"
    },
    {
      "name": "Corporate Gift Cards for Your Business | Flipkart",
      "normalized_name": "corporate_gift_cards_for_your_business___flipkart",
      "price": "N/A",
      "url": "https://www.flipkart.com/giftcard-b2b-at-store",
      "category": "unknown"
    },
    {
      "name": "Digital Gift Cards - Buy Digital Gift Cards Online at Best Prices In India | Flipkart.com",
      "normalized_name": "digital_gift_cards___buy_digital_gift_cards_online_at_best_prices_in_india___flipkart_com",
      "price": "\u20b98",
      "url": "https://www.flipkart.com/vas/gift-cards/digital-gift-cards/pr?sid=mcd%2C1ob%2Cdci&p%5B%5D=facets.price_range.from%3D10000&p%5B%5D=facets.price_range.to%3DMax&p%5B%5D=facets.type%255B%255D%3DTravel&p%5B%5D=facets.type%255B%255D%3DEntertainment&p%5B%5D=facets.type%255B%255D%3DSpa%2B%2526%2BSalon&p%5B%5D=facets.type%255B%255D%3DElectronics&p%5B%5D=facets.type%255B%255D%3DHome%2B%2526%2BKitchen&p%5B%5D=facets.type%255B%255D%3DFood%2B%2526%2BBeverages&p%5B%5D=facets.type%255B%255D%3DApps%2B%2526%2BSoftware&p%5B%5D=facets.type%255B%255D%3DGold%2Band%2BDiamonds&p%5B%5D=facets.type%255B%255D%3DLifestyle&pageUID=1752752359420383&otracker=clp_creative_card_1_7.creativeCard.CREATIVE_CARD_the-gift-card-store_OV6RR3ZSWNOS&fm=neo%2Fmerchandising&iid=M_6386fec3-c4cd-4b4a-b1ca-1d38a6b1651a_7.OV6RR3ZSWNOS&ppt=None&ppn=None&ssid=we9qihzogg0000001771434649458",
      "category": "unknown"
    },
    {
      "name": "Digital Gift Cards - Buy Digital Gift Cards Online at Best Prices In India | Flipkart.com",
      "normalized_name": "digital_gift_cards___buy_digital_gift_cards_online_at_best_prices_in_india___flipkart_com",
      "price": "\u20b9400",
      "url": "https://www.flipkart.com/vas/gift-cards/digital-gift-cards/pr?sid=mcd%2C1ob%2Cdci&p%5B%5D=facets.price_range.from%3DMin&p%5B%5D=facets.price_range.to%3D2500&p%5B%5D=facets.type%255B%255D%3DTravel&p%5B%5D=facets.type%255B%255D%3DEntertainment&p%5B%5D=facets.type%255B%255D%3DSpa%2B%2526%2BSalon&p%5B%5D=facets.type%255B%255D%3DElectronics&p%5B%5D=facets.type%255B%255D%3DHome%2B%2526%2BKitchen&p%5B%5D=facets.type%255B%255D%3DFood%2B%2526%2BBeverages&p%5B%5D=facets.type%255B%255D%3DApps%2B%2526%2BSoftware&p%5B%5D=facets.type%255B%255D%3DGold%2Band%2BDiamonds&p%5B%5D=facets.type%255B%255D%3DLifestyle&pageUID=1752752149106377&otracker=clp_creative_card_4_7.creativeCard.CREATIVE_CARD_the-gift-card-store_SIVD33ZRZUQZ&fm=neo%2Fmerchandising&iid=M_6386fec3-c4cd-4b4a-b1ca-1d38a6b1651a_7.SIVD33ZRZUQZ&ppt=None&ppn=None&ssid=we9qihzogg0000001771434649458",
      "category": "unknown"
    },
    {
      "name": "Buy Gift Cards & Vouchers Online for All Occasions | Flipkart",
      "normalized_name": "buy_gift_cards___vouchers_online_for_all_occasions___flipkart",
      "price": "N/A",
      "url": "https://www.flipkart.com/the-gift-card-store?otracker=footer_navlinks",
      "category": "unknown"
    }
  ]
}